itchiodl/__init__.py
itchiodl/bundle.py
itchiodl/bundle_tool/__main__.py
itchiodl/downloader/__main__.py
itchiodl/game.py
itchiodl/library.py
itchiodl/login.py
itchiodl/utils.py
itchiodl-2.3.0.dist-info/LICENSE
itchiodl-2.3.0.dist-info/METADATA
itchiodl-2.3.0.dist-info/WHEEL
itchiodl-2.3.0.dist-info/entry_points.txt
itchiodl-2.3.0.dist-info/RECORD
